ccproxy/__init__.py
ccproxy/__main__.py
ccproxy/classifier.py
ccproxy/cli.py
ccproxy/config.py
ccproxy/handler.py
ccproxy/hooks.py
ccproxy/router.py
ccproxy/rules.py
ccproxy/utils.py
ccproxy/templates/ccproxy.yaml
ccproxy/templates/config.yaml
claude_ccproxy-1.2.0.dist-info/METADATA
claude_ccproxy-1.2.0.dist-info/WHEEL
claude_ccproxy-1.2.0.dist-info/entry_points.txt
claude_ccproxy-1.2.0.dist-info/licenses/LICENSE
claude_ccproxy-1.2.0.dist-info/RECORD
