Metadata-Version: 2.4
Name: claude-ccproxy
Version: 1.2.0
Summary: Scriptable Claude Code LiteLLM-based proxy
License: AGPL-3.0-or-later
License-File: LICENSE
Keywords: ai,litellm,llm,proxy,routing
Classifier: Development Status :: 5 - Production/Stable
Classifier: Intended Audience :: Developers
Classifier: License :: OSI Approved :: GNU Affero General Public License v3 or later (AGPLv3+)
Classifier: Programming Language :: Python :: 3
Classifier: Programming Language :: Python :: 3.11
Classifier: Programming Language :: Python :: 3.12
Classifier: Topic :: Software Development :: Libraries :: Python Modules
Requires-Python: >=3.11
Requires-Dist: anthropic>=0.39.0
Requires-Dist: attrs>=23.0.0
Requires-Dist: fasteners>=0.19.0
Requires-Dist: httpx>=0.27.0
Requires-Dist: langfuse<3.0.0,>=2.0.0
Requires-Dist: litellm[proxy]>=1.13.0
Requires-Dist: prisma>=0.15.0
Requires-Dist: prometheus-client>=0.18.0
Requires-Dist: psutil>=5.9.0
Requires-Dist: pydantic-settings>=2.0.0
Requires-Dist: pydantic>=2.0.0
Requires-Dist: python-dotenv>=1.0.0
Requires-Dist: pyyaml>=6.0
Requires-Dist: rich>=13.7.1
Requires-Dist: structlog>=24.0.0
Requires-Dist: tiktoken>=0.5.0
Requires-Dist: types-psutil>=7.0.0.20250601
Requires-Dist: tyro>=0.7.0
Requires-Dist: watchdog>=3.0.0
Provides-Extra: dev
Requires-Dist: coverage[toml]>=7.0.0; extra == 'dev'
Requires-Dist: mypy>=1.8.0; extra == 'dev'
Requires-Dist: pre-commit>=3.5.0; extra == 'dev'
Requires-Dist: pytest-asyncio>=0.23.0; extra == 'dev'
Requires-Dist: pytest-cov>=4.0.0; extra == 'dev'
Requires-Dist: pytest>=8.0.0; extra == 'dev'
Requires-Dist: ruff>=0.1.0; extra == 'dev'
Requires-Dist: types-pyyaml>=6.0.0; extra == 'dev'
Requires-Dist: types-requests>=2.31.0; extra == 'dev'
